pychatbot/__init__.py
pychatbot/client.py
pychatbot/types.py
dada_pychatbot-0.1.0.dist-info/METADATA
dada_pychatbot-0.1.0.dist-info/WHEEL
dada_pychatbot-0.1.0.dist-info/RECORD
