Metadata-Version: 2.4
Name: dada-pychatbot
Version: 0.1.0
Summary: Python SDK for chatbot platform
Project-URL: Homepage, https://github.com/dada/pychatbot
Project-URL: Repository, https://github.com/dada/pychatbot.git
Author-email: dada <dada@example.com>
License-Expression: MIT
Keywords: chatbot,python,sdk
Classifier: Development Status :: 3 - Alpha
Classifier: Intended Audience :: Developers
Classifier: License :: OSI Approved :: MIT License
Classifier: Programming Language :: Python :: 3
Classifier: Programming Language :: Python :: 3.8
Classifier: Programming Language :: Python :: 3.9
Classifier: Programming Language :: Python :: 3.10
Classifier: Programming Language :: Python :: 3.11
Requires-Python: >=3.8
